hpc_scripts/gui.py
hpc_scripts/slurm_config.py
hpc_scripts/brainglobe_hpc/brainglobe_array_job_constructor.py
hpc_scripts/brainglobe_hpc/brainreg_commands.py
hpc_scripts/brainglobe_hpc/brainreg_single_job_script_constructor.py
hpc_scripts/brainglobe_hpc/cellfinder_commands.py
hpc_scripts/brainglobe_hpc/shared_functions.py
hpc_scripts/dlc_legacy/run_dlc_tracking.py
hpc_scripts-0.1.0.dist-info/METADATA
hpc_scripts-0.1.0.dist-info/WHEEL
hpc_scripts-0.1.0.dist-info/entry_points.txt
hpc_scripts-0.1.0.dist-info/top_level.txt
hpc_scripts-0.1.0.dist-info/RECORD
