Metadata-Version: 2.4
Name: hpc_scripts
Version: 0.1.0
Summary: A short description of the project.
Author-email: Stephen Lenzi <stephen.lenzi@gmail.com>
Requires-Python: >=3.8
Requires-Dist: fire
Requires-Dist: pyyaml
Requires-Dist: cached-property
Requires-Dist: xpmtd
Requires-Dist: magicgui
Requires-Dist: PyQt5; platform_system == "Windows"
Requires-Dist: PyQt5==5.14; platform_system == "Linux"
